README.rst
setup.cfg
setup.py
xlscript/__init__.py
xlscript.egg-info/PKG-INFO
xlscript.egg-info/SOURCES.txt
xlscript.egg-info/dependency_links.txt
xlscript.egg-info/requires.txt
xlscript.egg-info/top_level.txt