Metadata-Version: 1.1
Name: xlscript
Version: 0.0.4
Summary: Python SDK for phpexcel-api
Home-page: https://github.com/easecloud/xlscript
Author: EaseCloud Co. Ltd.
Author-email: 57082212@qq.com
License: MIT License
Download-URL: https://github.com/easecloud/xlscript/tarball/0.0.4
Keywords: excel,microsoft,xlscript,download
Platform: any
